zbxepics/__init__.py
zbxepics/casender/__init__.py
zbxepics/casender/casender.py
zbxepics/casender/peekqueue.py
zbxepics/casender/item/__init__.py
zbxepics/casender/item/factory.py
zbxepics/casender/item/intervalitem.py
zbxepics/casender/item/monitoritem.py
zbxepics/logging/__init__.py
zbxepics/logging/logger.py
zabbix_epics_py-1.1.0.dist-info/LICENSE
zabbix_epics_py-1.1.0.dist-info/METADATA
zabbix_epics_py-1.1.0.dist-info/WHEEL
zabbix_epics_py-1.1.0.dist-info/top_level.txt
zabbix_epics_py-1.1.0.dist-info/RECORD
