Metadata-Version: 2.2
Name: zabbix-epics-py
Version: 1.1.0
Summary: Zabbix-EPICS for Python
Home-page: https://github.com/sasaki77/zabbix-epics-py
Maintainer: Shinya Sasaki
Classifier: Programming Language :: Python :: 3
Classifier: License :: OSI Approved :: MIT License
Classifier: Operating System :: OS Independent
License-File: LICENSE
Requires-Dist: future
Requires-Dist: zabbix_utils
Requires-Dist: pyepics
Provides-Extra: develop
Requires-Dist: pytest; extra == "develop"
Requires-Dist: pytest-cov; extra == "develop"
Requires-Dist: pycodestyle; extra == "develop"
Dynamic: classifier
Dynamic: description
Dynamic: description-content-type
Dynamic: home-page
Dynamic: maintainer
Dynamic: provides-extra
Dynamic: requires-dist
Dynamic: summary
